pycrunch/__init__.py
pycrunch/csvlib.py
pycrunch/cubes.py
pycrunch/elements.py
pycrunch/exporting.py
pycrunch/importing.py
pycrunch/ipython_ext.py
pycrunch/lemonpy.py
pycrunch/pandaslib.py
pycrunch/progress.py
pycrunch/shoji.py
pycrunch/users.py
pycrunch/variables.py
pycrunch/version.py
pycrunch-0.5.8.dist-info/COPYING
pycrunch-0.5.8.dist-info/COPYING.LESSER
pycrunch-0.5.8.dist-info/LICENSE
pycrunch-0.5.8.dist-info/METADATA
pycrunch-0.5.8.dist-info/WHEEL
pycrunch-0.5.8.dist-info/top_level.txt
pycrunch-0.5.8.dist-info/zip-safe
pycrunch-0.5.8.dist-info/RECORD
