Metadata-Version: 2.1
Name: pycrunch
Version: 0.5.8
Summary: Crunch.io Client Library
Home-page: https://github.com/Crunch-io/pycrunch
Author: Crunch.io
Author-email: dev@crunch.io
License: LGPL
Platform: UNKNOWN
Classifier: Programming Language :: Python
Classifier: Topic :: Software Development :: Libraries :: Python Modules
Requires-Python: >=2.7,!=3.0.*,!=3.1.*,!=3.2.*,!=3.3.*
Requires-Dist: requests (>=2.14.0)
Requires-Dist: six
Provides-Extra: pandas
Requires-Dist: pandas ; (python_version=="2.7" or python_version>="3.5") and extra == 'pandas'
Requires-Dist: pandas (~=0.19.0) ; (python_version=="3.4") and extra == 'pandas'
Provides-Extra: testing
Requires-Dist: mock ; extra == 'testing'
Requires-Dist: pytest ; extra == 'testing'
Requires-Dist: pytest-cov ; extra == 'testing'
Requires-Dist: pandas ; (python_version=="2.7" or python_version>="3.5") and extra == 'testing'
Requires-Dist: pandas (~=0.19.0) ; (python_version=="3.4") and extra == 'testing'
